{
  "meta": {
    "language": "ada",
    "language_version": "2012",
    "language_name": "Ada"
  },
  "categories": {
    "Numerical": [
      "boolean",
      "signed_integer_8_bit",
      "signed_integer_as_object",
      "signed_float_16_bit",
      "signed_float_32_bit",
      "signed_float_64_bit",
      "signed_float_as_object"
    ],
    "Strings": [
      "character",
      "string_as_array"
    ],
    "Complex Numbers": [
      "complex_as_object",
      "real_number_part",
      "imaginary_number_part"
    ]
  },
  "data_types": {
    "boolean": {

      "code": "boolean"
    },
    "signed_integer_8_bit": {
      "comment": "In Ada you can define your own integer types by declaring it like this with a range, the compiler then chooses a representation that can hold all desired values.",
      "code": "type My_Int is range -128 .. 127;"
    },
    "signed_integer_as_object": {
      "code": "Integer"
    },
    "signed_float_64_bit": {
      "comment": "Like with integers Ada let's you create your own floating point types as well by specifying the desired amount of decimal digits",
      "code": "type My_Float is digits 15;"
    },
    "signed_float_as_object": {
      "code": "Float"
    },
    "character": {
      "code": "Character"
    },
    "string_as_array": {
      "code": "String"
    },
    "complex_as_object": {
      "comment": "Ada's Complex type is found in the library `Ada.Numerics.Generic_Complex_Types`",
      "code": "Complex"
    },
    "real_number_part": {
      "code": "Re (Complex_Number);"
    },
    "imaginary_number_part": {
      "code": "Im (Complex_Number);"
    }
  }
}
